vic/__init__.py
vic/arithmetic.py
vic/checkerboard.py
vic/decrypt.py
vic/encrypt.py
vic/ik.py
vic/main.py
vic/message_indicator.py
vic/rotation.py
vic/transposition.py
vic/util.py
vic-0.0.1.dist-info/DESCRIPTION.rst
vic-0.0.1.dist-info/METADATA
vic-0.0.1.dist-info/RECORD
vic-0.0.1.dist-info/WHEEL
vic-0.0.1.dist-info/entry_points.txt
vic-0.0.1.dist-info/metadata.json
vic-0.0.1.dist-info/top_level.txt
