Metadata-Version: 1.1
Name: vic
Version: 0.0.1
Summary: Implementation of the pen-and-paper VIC cipher
Home-page: https://github.com/kyrias/vic
Author: Johannes Löthberg
Author-email: johannes@kyriasis.com
License: ISC
Keywords: vic cipher cryptography soviet reino häyhänen
Platform: UNKNOWN
Classifier: Development Status :: 3 - Alpha
Classifier: Intended Audience :: End Users/Desktop
Classifier: Topic :: Security :: Cryptography
Classifier: License :: OSI Approved :: ISC License (ISCL)
Classifier: Programming Language :: Python :: 3
Classifier: Programming Language :: Python :: 3.5
